{
  "manifest_version": 2,
  "name": "Chess Assistant",
  "version": "1.0.0",
  "description": "Free chess analysis assistant using Stockfish for chess.com/lichess.org",
  "applications": {
    "gecko": {
      "id": "chess-assistant@example.com",
      "strict_min_version": "57.0"
    }
  },
  "permissions": [
    "storage",
    "https://www.chess.com/*",
    "https://lichess.org/*",
    "https://cdn.jsdelivr.net/*"
  ],
  "content_security_policy": "script-src 'self' https://cdn.jsdelivr.net 'wasm-eval'; object-src 'self'",
  "background": {
    "scripts": [
      "browser-polyfill.js",
      "background.js"
    ]
  },
  "content_scripts": [
    {
      "matches": [
        "https://www.chess.com/*",
        "https://lichess.org/*"
      ],
      "js": [
        "browser-polyfill.js",
        "content.js"
      ],
      "css": [
        "overlay.css"
      ],
      "run_at": "document_idle"
    }
  ],
  "web_accessible_resources": [
    "stockfish.js",
    "stockfish.wasm",
    "ecoA.json",
    "ecoB.json",
    "ecoC.json",
    "ecoD.json",
    "ecoE.json"
  ],
  "browser_action": {
    "default_popup": "popup.html",
    "default_icon": {
      "48": "icon.png",
      "96": "icon.png"
    }
  },
  "icons": {
    "48": "icon.png",
    "96": "icon.png"
  }
}